ipfind_m/__init__.py
ipfind_m/main.py
ipfind_m-0.1.2.dist-info/entry_points.txt
ipfind_m-0.1.2.dist-info/WHEEL
ipfind_m-0.1.2.dist-info/METADATA
ipfind_m-0.1.2.dist-info/RECORD
