Metadata-Version: 2.4
Name: ipfind-m
Version: 0.1.2
Summary: This tool for find domain ip address/IPv4/IPv6
Author-email: Microtip <ikhwan@gmail.com>
Requires-Python: >=3.8
Requires-Dist: rich
Requires-Dist: pyfiglet
Requires-Dist: requests
